deala/__init__.py
deala/deala_io.py
deala/files/.DS_Store
deala/files/DEALA_activities/.DS_Store
deala/files/DEALA_activities/construction.json
deala/files/DEALA_activities/electricity.json
deala/files/DEALA_activities/gas.json
deala/files/DEALA_activities/material_beer.json
deala/files/DEALA_activities/personal.json
deala/files/DEALA_activities/revenue.json
deala/files/DEALA_activities/transport.json
deala/files/DEALA_activities/waste.json
deala/files/Excel_datasets/.DS_Store
deala/files/Excel_datasets/DB_Energy.xlsx
deala/files/Excel_datasets/DB_Transport.xlsx
deala/files/Excel_datasets/pan_production/.DS_Store
deala/files/Excel_datasets/pan_production/Excel_BW2_non_stick_conventional.xlsx
deala/files/Excel_datasets/pan_production/Excel_BW2_non_stick_pan_recoatable.xlsx
deala/files/Excel_datasets/pan_production/Excel_BW2_stainless_steel.xlsx
deala/files/Excel_datasets/pan_production/input_materials.xlsx
deala/files/Excel_datasets/pan_production/input_materials_regioinvent.xlsx
deala/files/Excel_datasets/pan_production/output_materials.xlsx
deala/files/Excel_datasets/pan_production/~$output_materials.xlsx
deala/files/Excel_datasets/pan_production/results/.DS_Store
deala/files/Excel_datasets/pan_production/results/Case1/pan_production_impact_deala_cost.xlsx
deala/files/Excel_datasets/pan_production/results/Case1/pan_production_impact_deala_profit.xlsx
deala/files/Excel_datasets/pan_production/results/Case1/result_process_Attaching handle_Non-stick pan (conventional)_remind_SSP2-Base_ecoSpold02_CN.xlsx
deala/files/Excel_datasets/pan_production/results/Case1/result_process_Attaching handle_Non-stick pan (conventional)_remind_SSP2-Base_ecoSpold02_DE.xlsx
deala/files/Excel_datasets/pan_production/results/Case1/result_process_Attaching handle_Non-stick pan (conventional)_remind_SSP2-Base_ecoSpold02_GLO.xlsx
deala/files/Excel_datasets/pan_production/results/Case1/result_process_Attaching handle_Non-stick pan (conventional)_remind_SSP2-Base_ecoSpold02_US.xlsx
deala-1.3.5.dist-info/licenses/LICENSE
deala-1.3.5.dist-info/METADATA
deala-1.3.5.dist-info/WHEEL
deala-1.3.5.dist-info/top_level.txt
deala-1.3.5.dist-info/RECORD
