Metadata-Version: 2.4
Name: deala
Version: 1.3.5
Summary: DEALA can be used for the economic assessment in Life Cycle Costing or Life Cycle Sustainability Assessment studies within Brightway2
Author-email: Jan-Linus Popien <j.popien@tu-braunschweig.de>
Keywords: LCC,characterization,brightway2,sustainability
Requires-Python: ==3.11.8
License-File: LICENSE
Requires-Dist: matplotlib>=3.10.7
Requires-Dist: premise==2.2.9
Requires-Dist: toml>=0.10.2
Requires-Dist: tqdm>=4.67.1
Requires-Dist: plotly>=6.4.0
Requires-Dist: regioinvent
Requires-Dist: wurst==0.4.0
Requires-Dist: brightway2>=2.4.7; sys_platform != "darwin"
Requires-Dist: scikit-umfpack>=0.4.2; sys_platform == "darwin"
Requires-Dist: brightway2==2.4.2; sys_platform == "darwin"
Requires-Dist: bw2io==0.8.8; sys_platform == "darwin"
Requires-Dist: pandas>=1.5.1
Requires-Dist: numpy==1.23.5; sys_platform != "darwin"
Requires-Dist: numpy==1.23.0; sys_platform == "darwin"
Requires-Dist: nbformat>=5.10.4
Requires-Dist: seaborn>=0.13.2
Requires-Dist: deala>=1.3.4
Requires-Dist: countryinfo>=0.1.2
Requires-Dist: pyparadiso; sys_platform == "win32"
Dynamic: license-file
